tagger/__init__.py
tagger/context_menu.py
tagger/shared.py
tagger/view.py
miz_tagger-0.0.1.dist-info/METADATA
miz_tagger-0.0.1.dist-info/WHEEL
miz_tagger-0.0.1.dist-info/entry_points.txt
miz_tagger-0.0.1.dist-info/top_level.txt
miz_tagger-0.0.1.dist-info/RECORD
