Metadata-Version: 2.1
Name: miz-tagger
Version: 0.0.1
Summary: A tagger system to manage files
Author-email: MIZiper <miziper@163.com>
License: Apache-2.0
Project-URL: Homepage, http://mizip.net/
Project-URL: Repository, https://github.com/MIZiper/MizTagger-pywin.git
Keywords: tag,label,resource,filter
Classifier: Environment :: Win32 (MS Windows)
Requires-Python: >=3.8
Requires-Dist: pywin32
Requires-Dist: pyqt5
